1bit_adc/test_three_bit_adc.v
// sch_path: /headless/Documents/1bit_adc/test_three_bit_adc.sch
module test_three_bit_adc
(
  output wire done,
  output wire [2:0] sel_wire,
  input wire RESET,
  input wire OUT_DIGITAL,
  input wire CLK
);
wire reset ;
wire add ;
wire clk ;

three_bit_adc
three_bit_adc ( 
 .clk( clk ),
 .sel_wire( sel_wire[2:0] ),
 .add( add ),
 .reset( reset ),
 .done( done )
);


.option savecurrents
.param vdd=1.8
*.param clk=300n
VVDD VDD 0 DC {vdd}
VCLK CLK 0 PULSE(0 1.8 0   1n 1n 40n 80n)
VOUT_DIGITAL OUT_DIGITAL 0 PULSE(0 1.8 0   1n 1n 10n 80n)
VRESET RESET 0 PULSE(0 1.8 0 1n 1n 40n 800n)
VVSS VSS 0 DC 0
.tran 2n 7000n

.control
save all
echo TRAN
run
write 3bit_dac.raw all
.endc
.end

endmodule

// expanding   symbol:  /headless/Documents/1bit_adc/three_bit_adc.sym # of pins=5
// sym_path: /headless/Documents/1bit_adc/three_bit_adc.sym
// sch_path: /headless/Documents/1bit_adc/three_bit_adc.sch
module three_bit_adc
(
  input wire clk,
  output wire [2:0] sel_wire,
  input wire add,
  input wire reset,
  output wire done
);
reg [2:0] in_sel;  // Internal signal for simulator visibilityi
reg [2:0] sel;
reg reg_clk;
reg reg_reset;
reg reg_add;
 assign sel_wire = sel;	
  assign done = (sel == 3'b000) | (sel == 3'b010) | (sel == 3'b100) | (sel == 3'b110 & !add) | (sel == 3'b111);

//assign add = reg_add;
//assign reset=reset_reg;
//assign reg_clk=clk;
     /* SIMULATION CODE 
   initial reg_clk=0;
   	always #4 reg_clk = ~reg_clk;
      initial begin
	  reg_reset=0;
	  reg_add=0;
	  $display("%03b %01b",sel, reg_clk);
	  #700 $finish;
    end 
	always begin
		#100;
		reg_reset=1;
		#8;
		reg_reset=0;
	end
	always begin
		#($random % 2+2);
		reg_add=~reg_add;	
	end
	*/ 
    /*initial begin
	$dumpfile("dumpfile.vcd");
	$dumpvars(0);
	end*/
	always @(posedge clk) begin
        if (reset) begin
	    sel = 3'b011;  // Reset to default value
            in_sel = 3'b000;
        end
        else begin
            in_sel = sel;  // Capture current sel value for reference
            if (add) begin // comparator told us that prvs sel guess was too low
                case (in_sel)
                    3'b000: sel <= 3'b000;
                    3'b001: sel <= 3'b010;
                    3'b010: sel <= 3'b010;           
                    3'b011: sel <= 3'b101;
                    3'b100: sel <= 3'b100;
                    3'b101: sel <= 3'b110;
                    3'b110: sel <= 3'b111;
                    3'b111: sel <= 3'b111;
                    default: sel <= 3'b011;
                endcase
            end
            else begin // comp told us prvs sel guess was too high
                case (in_sel)
                    3'b000: sel <= 3'b000;
                    3'b001: sel <= 3'b000;
                    3'b010: sel <= 3'b010;
                    3'b011: sel <= 3'b001;
                    3'b100: sel <=3'b100;
                    3'b101: sel <= 3'b100;
                    3'b110: sel <= 3'b110;
                    3'b111: sel <= 3'b111;
                    default: sel <= 3'b011;
                endcase
            end
        end    
    end
      

endmodule

1bit_adc/dumpfile.vcd
$date
	Fri Aug  8 18:01:59 2025
$end
$version
	Icarus Verilog
$end
$timescale
	1s
$end
$scope module three_bit_adc $end
$var wire 1 ! clk $end
$var wire 1 " done $end
$var wire 1 # reset $end
$var wire 3 $ sel_wire [2:0] $end
$var wire 1 % add $end
$var reg 3 & in_sel [2:0] $end
$var reg 1 % reg_add $end
$var reg 1 ' reg_clk $end
$var reg 1 ( reg_reset $end
$var reg 3 ) sel [2:0] $end
$upscope $end
$enddefinitions $end
$comment Show the parameter values. $end
$dumpall
$end
#0
$dumpvars
bx )
0(
0'
bx &
0%
bx $
0#
x"
0!
$end
#2
1%
#3
0%
#4
0"
b11 $
b11 )
1%
1!
1'
#5
0%
#8
1%
0!
0'
#11
0%
#12
b101 $
b101 )
b11 &
1%
1!
1'
#14
0%
#16
0!
0'
#17
1%
#20
1"
b100 $
b100 )
b101 &
0%
1!
1'
#22
1%
#24
0!
0'
#25
0%
#28
b100 &
1%
1!
1'
#30
0%
#32
0!
0'
#33
1%
#35
0%
#36
1%
1!
1'
#38
0%
#40
0!
0'
#41
1%
#42
0%
#44
1%
1!
1'
#47
0%
#48
0!
0'
#49
1%
#51
0%
#52
1!
1'
#53
1%
#54
0%
#56
1%
0!
0'
#57
0%
#58
1%
#59
0%
#60
1%
1!
1'
#62
0%
#64
1%
0!
0'
#66
0%
#68
1%
1!
1'
#69
0%
#71
1%
#72
0%
0!
0'
#73
1%
#74
0%
#76
1!
1'
#77
1%
#78
0%
#80
1%
0!
0'
#82
0%
#84
1!
1'
#85
1%
#86
0%
#88
0!
0'
#89
1%
#91
0%
#92
1!
1'
#93
1%
#95
0%
#96
0!
0'
#97
1%
#99
0%
#100
0"
b0 &
b11 $
b11 )
1!
1'
1#
1(
#102
1%
#104
0%
0!
0'
#106
1%
#107
0%
#108
b1 $
b1 )
b11 &
1!
1'
0#
0(
#110
1%
#112
0%
0!
0'
#114
1%
#116
1"
b0 $
b0 )
b1 &
0%
1!
1'
#118
1%
#120
0%
0!
0'
#121
1%
#122
0%
#124
b0 &
1!
1'
#125
1%
#128
0%
0!
0'
#129
1%
#131
0%
#132
1!
1'
#133
1%
#136
0%
0!
0'
#139
1%
#140
1!
1'
#142
0%
#144
1%
0!
0'
#146
0%
#148
1!
1'
#149
1%
#152
0%
0!
0'
#154
1%
#155
0%
#156
1%
1!
1'
#158
0%
#159
1%
#160
0!
0'
#162
0%
#163
1%
#164
1!
1'
#165
0%
#166
1%
#167
0%
#168
0!
0'
#169
1%
#171
0%
#172
1!
1'
#173
1%
#175
0%
#176
1%
0!
0'
#179
0%
#180
1!
1'
#181
1%
#183
0%
#184
0!
0'
#186
1%
#188
1!
1'
#189
0%
#192
1%
0!
0'
#193
0%
#196
1%
1!
1'
#198
0%
#200
0!
0'
#201
1%
#204
0%
1!
1'
#205
1%
#207
0%
#208
0!
0'
1#
1(
#209
1%
#211
0%
#212
0"
b11 $
b11 )
1!
1'
#213
1%
#215
0%
#216
0!
0'
0#
0(
#217
1%
#219
0%
#220
b1 $
b1 )
b11 &
1!
1'
#222
1%
#223
0%
#224
1%
0!
0'
#225
0%
#226
1%
#228
1"
b0 $
b0 )
b1 &
0%
1!
1'
#231
1%
#232
0%
0!
0'
#234
1%
#236
b0 &
0%
1!
1'
#239
1%
#240
0%
0!
0'
#242
1%
#243
0%
#244
1%
1!
1'
#245
0%
#248
1%
0!
0'
#250
0%
#252
1%
1!
1'
#254
0%
#256
0!
0'
#257
1%
#259
0%
#260
1!
1'
#261
1%
#263
0%
#264
1%
0!
0'
#265
0%
#267
1%
#268
1!
1'
#269
0%
#270
1%
#272
0%
0!
0'
#274
1%
#276
0%
1!
1'
#279
1%
#280
0!
0'
#281
0%
#283
1%
#284
1!
1'
#286
0%
#288
1%
0!
0'
#289
0%
#292
1%
1!
1'
#293
0%
#296
1%
0!
0'
#297
0%
#299
1%
#300
1!
1'
#301
0%
#303
1%
#304
0!
0'
#306
0%
#308
1%
1!
1'
#310
0%
#312
0!
0'
#313
1%
#316
0"
b11 $
b11 )
0%
1!
1'
1#
1(
#318
1%
#320
0%
0!
0'
#322
1%
#323
0%
#324
b101 $
b101 )
b11 &
1%
1!
1'
0#
0(
#326
0%
#328
1%
0!
0'
#330
0%
#331
1%
#332
b110 $
b110 )
b101 &
1!
1'
#334
1"
0%
#336
0"
1%
0!
0'
#338
1"
0%
#340
b111 $
b111 )
1"
b110 &
1%
1!
1'
#341
0%
#343
1%
#344
0!
0'
#345
0%
#346
1%
#348
b111 &
0%
1!
1'
#350
1%
#352
0%
0!
0'
#355
1%
#356
1!
1'
#357
0%
#358
1%
#360
0!
0'
#361
0%
#363
1%
#364
1!
1'
#365
0%
#367
1%
#368
0!
0'
#369
0%
#372
1%
1!
1'
#374
0%
#376
1%
0!
0'
#378
0%
#380
1%
1!
1'
#381
0%
#382
1%
#384
0!
0'
#385
0%
#387
1%
#388
0%
1!
1'
#391
1%
#392
0%
0!
0'
#394
1%
#396
0%
1!
1'
#399
1%
#400
0%
0!
0'
#401
1%
#404
0%
1!
1'
#405
1%
#407
0%
#408
0!
0'
#410
1%
#411
0%
#412
1!
1'
#413
1%
#415
0%
#416
0!
0'
#417
1%
#419
0%
#420
1!
1'
#422
1%
#423
0%
#424
0!
0'
1#
1(
#425
1%
#427
0%
#428
0"
b0 &
b11 $
b11 )
1%
1!
1'
#430
0%
#432
1%
0!
0'
0#
0(
#433
0%
#435
1%
#436
b101 $
b101 )
b11 &
1!
1'
#437
0%
#438
1%
#440
0%
0!
0'
#442
1%
#444
b110 $
b110 )
b101 &
1!
1'
#445
1"
0%
#448
0"
1%
0!
0'
#449
1"
0%
#451
0"
1%
#452
1"
b111 $
b111 )
b110 &
1!
1'
#453
0%
#455
1%
#456
0!
0'
#458
0%
#460
b111 &
1%
1!
1'
#462
0%
#464
0!
0'
#465
1%
#467
0%
#468
1!
1'
#469
1%
#471
0%
#472
0!
0'
#473
1%
#474
0%
#476
1%
1!
1'
#478
0%
#480
1%
0!
0'
#483
0%
#484
1%
1!
1'
#486
0%
#487
1%
#488
0%
0!
0'
#489
1%
#492
0%
1!
1'
#494
1%
#495
0%
#496
1%
0!
0'
#499
0%
#500
1!
1'
#501
1%
#503
0%
#504
0!
0'
#506
1%
#508
0%
1!
1'
#510
1%
#511
0%
#512
0!
0'
#514
1%
#516
0%
1!
1'
#518
1%
#520
0!
0'
#521
0%
#523
1%
#524
1!
1'
#525
0%
#528
1%
0!
0'
#530
0%
#531
1%
#532
0"
b0 &
b11 $
b11 )
0%
1!
1'
1#
1(
#534
1%
#536
0!
0'
#537
0%
#539
1%
#540
b1 $
b1 )
b11 &
0%
1!
1'
0#
0(
#542
1%
#544
0%
0!
0'
#547
1%
#548
1"
b10 $
b10 )
b1 &
1!
1'
#549
0%
#551
1%
#552
0!
0'
#553
0%
#554
1%
#555
0%
#556
b10 &
1%
1!
1'
#559
0%
#560
0!
0'
#562
1%
#564
0%
1!
1'
#567
1%
#568
0!
0'
#570
0%
#571
1%
#572
1!
1'
#573
0%
#575
1%
#576
0!
0'
#577
0%
#579
1%
#580
1!
1'
#581
0%
#583
1%
#584
0%
0!
0'
#587
1%
#588
0%
1!
1'
#591
1%
#592
0!
0'
#594
0%
#596
1!
1'
#597
1%
#598
0%
#600
1%
0!
0'
#601
0%
#602
1%
#603
0%
#604
1%
1!
1'
#607
0%
#608
0!
0'
#610
1%
#612
1!
1'
#613
0%
#614
1%
#616
0%
0!
0'
#618
1%
#619
0%
#620
1!
1'
#622
1%
#624
0%
0!
0'
#626
1%
#628
0%
1!
1'
#630
1%
#631
0%
#632
0!
0'
#633
1%
#635
0%
#636
1!
1'
#637
1%
#639
0%
#640
0!
0'
1#
1(
#641
1%
#643
0%
#644
0"
b0 &
b11 $
b11 )
1%
1!
1'
#646
0%
#648
1%
0!
0'
0#
0(
#651
0%
#652
b1 $
b1 )
b11 &
1!
1'
#653
1%
#655
0%
#656
0!
0'
#657
1%
#659
0%
#660
1"
b0 $
b0 )
b1 &
1!
1'
#662
1%
#663
0%
#664
0!
0'
#666
1%
#667
0%
#668
b0 &
1!
1'
#670
1%
#672
0%
0!
0'
#675
1%
#676
1!
1'
#678
0%
#679
1%
#680
0!
0'
#681
0%
#684
1%
1!
1'
#686
0%
#688
1%
0!
0'
#689
0%
#690
1%
#692
0%
1!
1'
#693
1%
#695
0%
#696
0!
0'
#697
1%
#700
0%
1!
1'
